Changelog
INSTALL.txt
LICENSE.txt
MANIFEST.in
README
TODO
common.py
pavement.py
setup.cfg
setup.py
./scikits/__init__.py
docs/DCT
docs/Makefile
docs/ext/docscrape.py
docs/ext/docscrape_sphinx.py
docs/ext/docscraper.py
docs/ext/numpydoc.py
docs/ext/only_directives.py
docs/html/genindex.html
docs/html/index.html
docs/html/intro.html
docs/html/lpc.html
docs/html/objects.inv
docs/html/search.html
docs/html/searchindex.js
docs/html/spectral.html
docs/html/_images/math/1765d5284db2db4459d30176f33a57491ec426fb.png
docs/html/_images/math/22db9aadc01c88f0aabdf544ae1d2312702d3e40.png
docs/html/_images/math/6a47ca0fe7cb276abc022af6ac88ddae1a9d6894.png
docs/html/_images/math/74d9b71f24bec81e0e4411b64e51c7ae415fb838.png
docs/html/_images/math/8eb08a23178927674ebf349af3b5f64731bc5194.png
docs/html/_images/math/9a12e9d6f5ca92a1dd316c5c7f6f90e81a09ab99.png
docs/html/_images/math/9e440b56e7843e34511f878937760cf51f4b6794.png
docs/html/_images/math/a228570da7959237d66f96ae0c859a76cf1fca98.png
docs/html/_images/math/e74851dc7226b517fb07b37a2e675d2413df1bca.png
docs/html/_images/math/f280b982f27e34ed430997ab1d8782e486bc4522.png
docs/html/_sources/index.txt
docs/html/_sources/intro.txt
docs/html/_sources/lpc.txt
docs/html/_sources/spectral.txt
docs/html/_static/contents.png
docs/html/_static/default.css
docs/html/_static/doctools.js
docs/html/_static/file.png
docs/html/_static/jquery.js
docs/html/_static/minus.png
docs/html/_static/navigation.png
docs/html/_static/plus.png
docs/html/_static/pygments.css
docs/html/_static/rightsidebar.css
docs/html/_static/searchtools.js
docs/html/_static/sphinxdoc.css
docs/html/_static/stickysidebar.css
docs/html/_static/traditional.css
docs/pdf/talkbox.pdf
docs/src/conf.py
docs/src/index.rst
docs/src/intro.rst
docs/src/lpc.rst
docs/src/spectral.rst
docs/src/.static/.gitignore
docs/src/examples/arspec_phoneme.py
docs/src/examples/periodogram_1.py
docs/src/examples/periodogram_2.py
docs/src/examples/voice-womanKP-01.wav
docs/src/examples/yop.m
scikits.talkbox.egg-info/PKG-INFO
scikits.talkbox.egg-info/SOURCES.txt
scikits.talkbox.egg-info/dependency_links.txt
scikits.talkbox.egg-info/namespace_packages.txt
scikits.talkbox.egg-info/not-zip-safe
scikits.talkbox.egg-info/requires.txt
scikits.talkbox.egg-info/top_level.txt
